{"chunkPosition":{"x":1,"y":-3,"z":0},"name":"","biomeMapList":[],"tileDataList":[{"x":32,"y":-75,"tileName":"White"},{"x":34,"y":-76,"tileName":"White"},{"x":36,"y":-77,"tileName":"White"},{"x":38,"y":-78,"tileName":"White"},{"x":40,"y":-78,"tileName":"White"},{"x":42,"y":-78,"tileName":"White"},{"x":42,"y":-78,"tileName":"White"},{"x":42,"y":-78,"tileName":"White"},{"x":43,"y":-78,"tileName":"White"},{"x":43,"y":-78,"tileName":"White"},{"x":49,"y":-78,"tileName":"White"},{"x":51,"y":-78,"tileName":"White"},{"x":52,"y":-78,"tileName":"White"},{"x":54,"y":-78,"tileName":"White"},{"x":56,"y":-78,"tileName":"White"},{"x":58,"y":-78,"tileName":"White"},{"x":60,"y":-77,"tileName":"White"},{"x":61,"y":-77,"tileName":"White"},{"x":63,"y":-76,"tileName":"White"}]}